scared/dashboard.py
scared/remote.py
scared_dashboard-0.1.0.dist-info/METADATA
scared_dashboard-0.1.0.dist-info/WHEEL
scared_dashboard-0.1.0.dist-info/RECORD
