Metadata-Version: 2.1
Name: scared-dashboard
Version: 0.1.0
Summary: 
Author: Aethor
Author-email: oow.autre@gmail.com
Requires-Python: >=3.8,<4.0
Classifier: Programming Language :: Python :: 3
Classifier: Programming Language :: Python :: 3.8
Classifier: Programming Language :: Python :: 3.9
Classifier: Programming Language :: Python :: 3.10
Classifier: Programming Language :: Python :: 3.11
Requires-Dist: dearpygui (>=1.7.0,<2.0.0)
Requires-Dist: fabric (>=3.2.1,<4.0.0)
